<text_block>
    <paragraph>
        Pense agora na possibilidade de um de vocês ou alguém de suas famílias terem algum tipo de dificuldade,
        a partir de determinada idade, para se locomover, ouvir, enxergar ou alcançar objetos.
    </paragraph>
    <paragraph>
        Em 1989, o arquiteto Ronald Mace, percebendo essa dificuldade, decidiu agrupar suas ideias para
        adaptar os ambientes em torno de um conceito que foi batizado de Design Universal, onde propôs que
        os produtos fossem desenhados para serem acessíveis para todas as pessoas independentes de idade
        ou condição físicas, assim como os prédios fossem projetados com ambientes adaptáveis às mudanças
        relacionadas à vida humana.
    </paragraph>
    <paragraph>
        Uma casa adaptável é aquela que pode ser transformada sem dificuldades. Já os espaços públicos
        precisam, por lei, ser adaptados a pessoas com deficiências. Alguns itens podem ser melhores tanto
        para os lugares públicos quanto para as casas. Ter uma casa adaptável significa tomar cuidado com esses
        detalhes e pensar na possibilidade de alguma mudança.
    </paragraph>
</text_block>
<source>
    Disponível em: <link>http://revistaepoca.globo.com/Revista/Epoca/0..EDR80173-5856.00.html</link>. Acesso em: 11 out. 2013 (adaptado).
</source>
<question>
    Considerando as informações do texto, avalie as afirmações a seguir.
    <question_options>
        <item>
            Os princípios do Design Universal devem inserir-se na atividade projetiva, visando o
            desenvolvimento de soluções que possibilitem a inclusão social relacionada aos diversos
            momentos da vida humana.
        </item>
        <item>
            Os parâmetros estratégicos para o Design Universal consideram prioritariamente os grupos
            sociais como consumidores em potencial, para isso são qualificados em segmentos específicos
            de mercado, tendo como finalidade o desenvolvimento de projetos adequados às realidades
            econômicas de cada grupo.
        </item>
        <item>
            A abordagem metodológica do Design Universal adota princípios da produção flexível, tendo como
            objetivo oferecer soluções baseadas na integração de aspectos projetivos relacionados tanto aos
            portadores de necessidades, quanto ao público em geral.
        </item>
        <item>
            O Design Universal, ao considerar o aspecto da longevidade na vida humana, contribui com a
            extensão do ciclo de vida do produto, pois reduz a rotatividade de soluções parciais em prol de
            resultados mais integrados e duradouros.
        </item>
    </question_options>
    É correto apenas o que se afirma em
</question>
<answer_options>
    <item>
        I e II.
    </item>
    <item>
        I e IV.
    </item>
    <item>
        II e III.
    </item>
    <item>
        I, III e IV.
    </item>
    <item>
        II, III e IV.
    </item>
</answer_options>